codetiming/__init__.py
codetiming/_timer.py
codetiming/_timers.py
codetiming/py.typed
codetiming-1.3.2.dist-info/LICENSE
codetiming-1.3.2.dist-info/WHEEL
codetiming-1.3.2.dist-info/METADATA
codetiming-1.3.2.dist-info/RECORD
